{"type":"TATE","from":"Tate Modern museum","artiste":"Joseph Mallord William Turner","artisteBio":"","date":"c.1806–7","title":"Dumblain Abbey, Scotland","subTitle":"","medium":"Graphite and watercolour on paper","dimensions":"support: 184 x 260 mm","medias":{"mini":"http://www.tate.org.uk/art/images/work/D/D08/D08157_8.jpg","medium":"http://www.tate.org.uk/art/images/work/D/D08/D08157_9.jpg","max":"http://www.tate.org.uk/art/images/work/D/D08/D08157_10.jpg","page":"http://www.tate.org.uk/art/artworks/turner-dumblain-abbey-scotland-d08157"},"classification":"on paper, unique","credits":"Accepted by the nation as part of the Turner Bequest 1856"}