{"type":"TATE","from":"Tate Modern museum","artiste":"Joseph Mallord William Turner","artisteBio":"","date":"1817","title":"Views Downstream from Mid-River: (1) to Bingen and Rüdesheim (Sketch of Rüdesheim to Right); (2) to St Roch’s Chapel, Bingen and Rüdesheim; (3) to Burg Klopp, Bingen, the Maüseturm and Burg Ehrenfels; (4) to the Church at Bornhofen and ‘The Brothers’","subTitle":"","medium":"Graphite on paper","dimensions":"support: 150 x 94 mm","medias":{"mini":"http://www.tate.org.uk/art/images/work/D/D12/D12841_8.jpg","medium":"http://www.tate.org.uk/art/images/work/D/D12/D12841_9.jpg","max":"http://www.tate.org.uk/art/images/work/D/D12/D12841_10.jpg","page":"http://www.tate.org.uk/art/artworks/turner-views-downstream-from-mid-river-1-to-bingen-and-rudesheim-sketch-of-rudesheim-to-d12841"},"classification":"on paper, unique","credits":"Accepted by the nation as part of the Turner Bequest 1856"}