{"type":"TATE","from":"Tate Modern museum","artiste":"Joseph Mallord William Turner","artisteBio":"","date":"c.1817–18","title":"?Design for a Picture","subTitle":"","medium":"Graphite on paper","dimensions":"support: 88 x 110 mm","medias":{"mini":"http://www.tate.org.uk/art/images/work/D/D13/D13234_8.jpg","medium":"http://www.tate.org.uk/art/images/work/D/D13/D13234_9.jpg","max":"http://www.tate.org.uk/art/images/work/D/D13/D13234_10.jpg","page":"http://www.tate.org.uk/art/artworks/turner-design-for-a-picture-d13234"},"classification":"on paper, unique","credits":"Accepted by the nation as part of the Turner Bequest 1856"}