{"type":"TATE","from":"Tate Modern museum","artiste":"Joseph Mallord William Turner","artisteBio":"","date":"1819","title":"The South-Western Corner of the Doge’s Palace, with the Campanile and the Piazzetta beyond","subTitle":"","medium":"Graphite on paper","dimensions":"support: 112 x 185 mm","medias":{"mini":"http://www.tate.org.uk/art/images/work/D/D14/D14412_8.jpg","medium":"http://www.tate.org.uk/art/images/work/D/D14/D14412_9.jpg","max":"http://www.tate.org.uk/art/images/work/D/D14/D14412_10.jpg","page":"http://www.tate.org.uk/art/artworks/turner-the-south-western-corner-of-the-doges-palace-with-the-campanile-and-the-piazzetta-d14412"},"classification":"on paper, unique","credits":"Accepted by the nation as part of the Turner Bequest 1856"}