{"type":"TATE","from":"Tate Modern museum","artiste":"Joseph Mallord William Turner","artisteBio":"","date":"1819","title":"Two Sketches of a Road among the Mountains, ?near Tivoli","subTitle":"","medium":"Graphite on paper","dimensions":"support: 112 x 186 mm","medias":{"mini":"http://www.tate.org.uk/art/images/work/D/D15/D15057_8.jpg","medium":"http://www.tate.org.uk/art/images/work/D/D15/D15057_9.jpg","max":"http://www.tate.org.uk/art/images/work/D/D15/D15057_10.jpg","page":"http://www.tate.org.uk/art/artworks/turner-two-sketches-of-a-road-among-the-mountains-near-tivoli-d15057"},"classification":"on paper, unique","credits":"Accepted by the nation as part of the Turner Bequest 1856"}