{"type":"TATE","from":"Tate Modern museum","artiste":"Joseph Mallord William Turner","artisteBio":"","date":"c.1824","title":"Tower, Etc., at Orford","subTitle":"","medium":"Graphite on paper","dimensions":"support: 115 x 188 mm","medias":{"mini":"http://www.tate.org.uk/art/images/work/D/D18/D18308_8.jpg","medium":"http://www.tate.org.uk/art/images/work/D/D18/D18308_9.jpg","max":"http://www.tate.org.uk/art/images/work/D/D18/D18308_10.jpg","page":"http://www.tate.org.uk/art/artworks/turner-tower-etc-at-orford-d18308"},"classification":"on paper, unique","credits":"Accepted by the nation as part of the Turner Bequest 1856"}