{"type":"TATE","from":"Tate Modern museum","artiste":"Joseph Mallord William Turner","artisteBio":"","date":"1830","title":"Ashby-de-la-Zouch from the West; Landscape Sketches and Diagrams","subTitle":"","medium":"Graphite on paper","dimensions":"support: 203 x 120 mm","medias":{"mini":"http://www.tate.org.uk/art/images/work/D/D22/D22150_8.jpg","medium":"http://www.tate.org.uk/art/images/work/D/D22/D22150_9.jpg","max":"http://www.tate.org.uk/art/images/work/D/D22/D22150_10.jpg","page":"http://www.tate.org.uk/art/artworks/turner-ashby-de-la-zouch-from-the-west-landscape-sketches-and-diagrams-d22150"},"classification":"on paper, unique","credits":"Accepted by the nation as part of the Turner Bequest 1856"}