{"type":"TATE","from":"Tate Modern museum","artiste":"Dame Elisabeth Frink","artisteBio":"","date":"1973–4","title":"Odysseus Meets his Son","subTitle":"","medium":"Lithograph on paper","dimensions":"image: 250 x 166 mm","medias":{"mini":"http://www.tate.org.uk/art/images/work/P/P06/P06202_8.jpg","medium":"http://www.tate.org.uk/art/images/work/P/P06/P06202_9.jpg","max":"http://www.tate.org.uk/art/images/work/P/P06/P06202_10.jpg","page":"http://www.tate.org.uk/art/artworks/frink-odysseus-meets-his-son-p06202"},"classification":"on paper, print","credits":"Presented by Curwen Studio through the Institute of Contemporary Prints 1975"}