{"type":"TATE","from":"Tate Modern museum","artiste":"Joseph Mallord William Turner","artisteBio":"","date":"1833","title":"(1) Schloss Rosenstein, near Stuttgart; (2) Gateway; The Church at Berg, Looking towards Cannstatt","subTitle":"","medium":"Graphite on paper","dimensions":"support: 165 x 110 mm","medias":{"mini":"http://www.tate.org.uk/art/images/work/D/D29/D29901_8.jpg","medium":"http://www.tate.org.uk/art/images/work/D/D29/D29901_9.jpg","max":"http://www.tate.org.uk/art/images/work/D/D29/D29901_10.jpg","page":"http://www.tate.org.uk/art/artworks/turner-1-schloss-rosenstein-near-stuttgart-2-gateway-the-church-at-berg-looking-towards-d29901"},"classification":"on paper, unique","credits":"Accepted by the nation as part of the Turner Bequest 1856"}