{"type":"TATE","from":"Tate Modern museum","artiste":"Lucian Freud","artisteBio":"","date":"1982","title":"Head of a Woman","subTitle":"","medium":"Etching on paper","dimensions":"image: 127 x 127 mm","medias":{"mini":"http://www.tate.org.uk/art/images/work/P/P07/P07782_8.jpg","medium":"http://www.tate.org.uk/art/images/work/P/P07/P07782_9.jpg","max":"http://www.tate.org.uk/art/images/work/P/P07/P07782_10.jpg","page":"http://www.tate.org.uk/art/artworks/freud-head-of-a-woman-p07782"},"classification":"on paper, print","credits":"Purchased 1982"}