{"type":"TATE","from":"Tate Modern museum","artiste":"Joan Miró","artisteBio":"","date":"1947","title":"Composition","subTitle":"","medium":"Etching on paper","dimensions":"image: 127 x 149 mm","medias":{"mini":"http://www.tate.org.uk/art/images/work/P/P77/P77064_8.jpg","medium":"http://www.tate.org.uk/art/images/work/P/P77/P77064_9.jpg","max":"http://www.tate.org.uk/art/images/work/P/P77/P77064_10.jpg","page":"http://www.tate.org.uk/art/artworks/miro-composition-p77064"},"classification":"on paper, print","credits":"Purchased 1984"}