{"type":"TATE","from":"Tate Modern museum","artiste":"Maurice Estève","artisteBio":"","date":"1956","title":"The Cicada","subTitle":"","medium":"Lithograph on paper","dimensions":"image: 402 x 402 mm","medias":{"mini":"http://www.tate.org.uk/art/images/work/P/P77/P77439_8.jpg","medium":"http://www.tate.org.uk/art/images/work/P/P77/P77439_9.jpg","max":"http://www.tate.org.uk/art/images/work/P/P77/P77439_10.jpg","page":"http://www.tate.org.uk/art/artworks/esteve-the-cicada-p77439"},"classification":"on paper, print","credits":"Purchased 1990"}