{"type":"TATE","from":"Tate Modern museum","artiste":"Bruce Nauman","artisteBio":"","date":"1973","title":"M Ampere","subTitle":"","medium":"Lithograph on paper","dimensions":"image: 762 x 1125 mm","medias":{"mini":"http://www.tate.org.uk/art/images/work/P/P77/P77437_8.jpg","medium":"http://www.tate.org.uk/art/images/work/P/P77/P77437_9.jpg","max":"http://www.tate.org.uk/art/images/work/P/P77/P77437_10.jpg","page":"http://www.tate.org.uk/art/artworks/nauman-m-ampere-p77437"},"classification":"on paper, print","credits":"Purchased 1990"}