{"type":"TATE","from":"Tate Modern museum","artiste":"Hannah Starkey","artisteBio":"","date":"1999","title":"Untitled - March 1999","subTitle":"","medium":"Photograph, colour, Chromogenic print, on paper mounted onto aluminium","dimensions":"image: 1220 x 1600 mm","medias":{"mini":"http://www.tate.org.uk/art/images/work/P/P78/P78332_8.jpg","medium":"http://www.tate.org.uk/art/images/work/P/P78/P78332_9.jpg","max":"http://www.tate.org.uk/art/images/work/P/P78/P78332_10.jpg","page":"http://www.tate.org.uk/art/artworks/starkey-untitled-march-1999-p78332"},"classification":"on paper, print","credits":"Purchased 1999"}