{"type":"TATE","from":"Tate Modern museum","artiste":"León Ferrari","artisteBio":"","date":"1995–6, 2007","title":"The Frigate ‘Escuela Libertad’ + Massera (Photo: Public Records Office) + Articles from the Newspapers ‘La Razón’ 6/9/76, ‘La Opinión’ 29/5 and 11/5/76 and ‘La Prensa’ 3/5/76","subTitle":"","medium":"Digital print on paper","dimensions":"support: 420 x 297 mm","medias":{"mini":"http://www.tate.org.uk/art/images/work/P/P79/P79555_8.jpg","medium":"http://www.tate.org.uk/art/images/work/P/P79/P79555_9.jpg","max":"http://www.tate.org.uk/art/images/work/P/P79/P79555_10.jpg","page":"http://www.tate.org.uk/art/artworks/ferrari-the-frigate-escuela-libertad-massera-photo-public-records-office-articles-from-the-p79555"},"classification":"on paper, print","credits":"Presented by Alicia and León Ferrari 2008"}