{"type":"TATE","from":"Tate Modern museum","artiste":"William N. Copley","artisteBio":"","date":"1956","title":"Place de l’Opéra","subTitle":"","medium":"Oil paint on canvas","dimensions":"support: 1159 x 810 mm","medias":{"mini":"http://www.tate.org.uk/art/images/work/T/T00/T00442_8.jpg","medium":"http://www.tate.org.uk/art/images/work/T/T00/T00442_9.jpg","max":"http://www.tate.org.uk/art/images/work/T/T00/T00442_10.jpg","page":"http://www.tate.org.uk/art/artworks/copley-place-de-lopera-t00442"},"classification":"painting","credits":"Presented by Sir Roland Penrose 1961"}