{"type":"TATE","from":"Tate Modern museum","artiste":"Dame Barbara Hepworth","artisteBio":"","date":"1937–8, cast 1963","title":"Single Form (Eikon)","subTitle":"","medium":"Bronze","dimensions":"object: 1480 x 280 x 320 mm, 77 kg","medias":{"mini":"http://www.tate.org.uk/art/images/work/T/T00/T00697_8.jpg","medium":"http://www.tate.org.uk/art/images/work/T/T00/T00697_9.jpg","max":"http://www.tate.org.uk/art/images/work/T/T00/T00697_10.jpg","page":"http://www.tate.org.uk/art/artworks/hepworth-single-form-eikon-t00697"},"classification":"sculpture","credits":"Presented by the artist 1964"}