{"type":"TATE","from":"Tate Modern museum","artiste":"William Scott","artisteBio":"","date":"1956","title":"Reclining Nude (Red Nude)","subTitle":"","medium":"Oil paint on canvas","dimensions":"support: 914 x 1524 mm\r\nframe: 964 x 1571 x 62 mm","medias":{"mini":"http://www.tate.org.uk/art/images/work/T/T00/T00811_8.jpg","medium":"http://www.tate.org.uk/art/images/work/T/T00/T00811_9.jpg","max":"http://www.tate.org.uk/art/images/work/T/T00/T00811_10.jpg","page":"http://www.tate.org.uk/art/artworks/scott-reclining-nude-red-nude-t00811"},"classification":"painting","credits":"Purchased 1965"}