{"type":"TATE","from":"Tate Modern museum","artiste":"Ben Nicholson OM","artisteBio":"","date":"1967","title":"1967 (Tuscan relief)","subTitle":"","medium":"Oil paint on hardboard on blockboard","dimensions":"object: 1518 x 1676 x 29 mm\r\n","medias":{"mini":"http://www.tate.org.uk/art/images/work/T/T00/T00929_8.jpg","medium":"http://www.tate.org.uk/art/images/work/T/T00/T00929_9.jpg","max":"http://www.tate.org.uk/art/images/work/T/T00/T00929_10.jpg","page":"http://www.tate.org.uk/art/artworks/nicholson-1967-tuscan-relief-t00929"},"classification":"relief","credits":"Purchased 1967"}