{"type":"TATE","from":"Tate Modern museum","artiste":"Colin Self","artisteBio":"","date":"1965","title":"Guard Dog on a Missile Base, No. 1","subTitle":"","medium":"Graphite, ink, watercolour and crayon on card","dimensions":"unconfirmed: 556 x 762 mm","medias":{"mini":"http://www.tate.org.uk/art/images/work/T/T01/T01850_8.jpg","medium":"http://www.tate.org.uk/art/images/work/T/T01/T01850_9.jpg","max":"http://www.tate.org.uk/art/images/work/T/T01/T01850_10.jpg","page":"http://www.tate.org.uk/art/artworks/self-guard-dog-on-a-missile-base-no-1-t01850"},"classification":null,"credits":"Purchased 1974"}