{"type":"TATE","from":"Tate Modern museum","artiste":"William Daniell","artisteBio":"","date":"date not known","title":"The Long-ships Light House, off the Lands End, Cornwall","subTitle":"","medium":"Aquatint on paper","dimensions":"image: 162 x 241 mm","medias":{"mini":"http://www.tate.org.uk/art/images/work/T/T02/T02722_8.jpg","medium":"http://www.tate.org.uk/art/images/work/T/T02/T02722_9.jpg","max":"http://www.tate.org.uk/art/images/work/T/T02/T02722_10.jpg","page":"http://www.tate.org.uk/art/artworks/daniell-the-long-ships-light-house-off-the-lands-end-cornwall-t02722"},"classification":"on paper, print","credits":"Presented by Tate Gallery Publications 1979"}