{"type":"TATE","from":"Tate Modern museum","artiste":"Rev. Matthew William Peters","artisteBio":"","date":"c.1777","title":"Lydia","subTitle":"","medium":"Oil paint on canvas","dimensions":"support: 642 x 770 mm","medias":{"mini":"http://www.tate.org.uk/art/images/work/T/T04/T04848_8.jpg","medium":"http://www.tate.org.uk/art/images/work/T/T04/T04848_9.jpg","max":"http://www.tate.org.uk/art/images/work/T/T04/T04848_10.jpg","page":"http://www.tate.org.uk/art/artworks/peters-lydia-t04848"},"classification":"painting","credits":"Purchased 1986"}