{"type":"TATE","from":"Tate Modern museum","artiste":"Philip James De Loutherbourg","artisteBio":"","date":"1786 or 1800","title":"Study of a Lime Kiln at the Foot of St Vincent’s Rock, Avon Gorge","subTitle":"","medium":"Pen and ink and graphite on paper","dimensions":"support: 80 x 124 mm","medias":{"mini":"http://www.tate.org.uk/art/images/work/D/D36/D36361_8.jpg","medium":"http://www.tate.org.uk/art/images/work/D/D36/D36361_9.jpg","max":"http://www.tate.org.uk/art/images/work/D/D36/D36361_10.jpg","page":"http://www.tate.org.uk/art/artworks/de-loutherbourg-study-of-a-lime-kiln-at-the-foot-of-st-vincents-rock-avon-gorge-d36361"},"classification":"on paper, unique","credits":"Accepted by the nation as part of the Turner Bequest 1856"}