{"type":"TATE","from":"Tate Modern museum","artiste":"after Joseph Mallord William Turner","artisteBio":"","date":"published 1859–61","title":"Mercury and Argus, engraved by Willmore","subTitle":"","medium":"Engraving on paper","dimensions":null,"medias":{"mini":"http://www.tate.org.uk/art/images/work/T/T06/T06347_8.jpg","medium":"http://www.tate.org.uk/art/images/work/T/T06/T06347_9.jpg","max":"http://www.tate.org.uk/art/images/work/T/T06/T06347_10.jpg","page":"http://www.tate.org.uk/art/artworks/turner-mercury-and-argus-engraved-by-willmore-t06347"},"classification":"on paper, print","credits":"Transferred from the British Museum 1988"}