{"type":"TATE","from":"Tate Modern museum","artiste":"Ben Nicholson OM","artisteBio":"","date":"1951","title":"Festival of Britain Mural","subTitle":"","medium":"3 works on hardboard, oil paint","dimensions":"displayed: 2165 x 4871 x 480 mm\r\nsupport: 2166 x 1241 mm\r\nsupport: 2167 x 2106 mm\r\nsupport: 2166 x 1518 mm","medias":{"mini":"http://www.tate.org.uk/art/images/work/T/T07/T07027_8.jpg","medium":"http://www.tate.org.uk/art/images/work/T/T07/T07027_9.jpg","max":"http://www.tate.org.uk/art/images/work/T/T07/T07027_10.jpg","page":"http://www.tate.org.uk/art/artworks/nicholson-festival-of-britain-mural-t07027"},"classification":"painting","credits":"Presented by the Court of the University of Edinburgh 1995"}