{"type":"TATE","from":"Tate Modern museum","artiste":"Jake Chapman, Dinos Chapman","artisteBio":"","date":"1993","title":"Little Death Machine (Castrated)","subTitle":"","medium":"Aluminium, steel, wood, glass, plastic, rubber, paper, leather, soap and coffee","dimensions":"displayed: 1384 x 742 x 943 mm","medias":{"mini":"http://www.tate.org.uk/art/images/work/T/T07/T07272_8.jpg","medium":"http://www.tate.org.uk/art/images/work/T/T07/T07272_9.jpg","max":"http://www.tate.org.uk/art/images/work/T/T07/T07272_10.jpg","page":"http://www.tate.org.uk/art/artworks/chapman-little-death-machine-castrated-t07272"},"classification":"sculpture","credits":"Presented anonymously 1997"}