{"type":"TATE","from":"Tate Modern museum","artiste":"Dame Elisabeth Frink","artisteBio":"","date":"c.1985","title":"Horseman (Robed)","subTitle":"","medium":"Plaster and steel on plaster base","dimensions":"object: 590 x 180 x 500 mm","medias":{"mini":"http://www.tate.org.uk/art/images/work/T/T07/T07421_8.jpg","medium":"http://www.tate.org.uk/art/images/work/T/T07/T07421_9.jpg","max":"http://www.tate.org.uk/art/images/work/T/T07/T07421_10.jpg","page":"http://www.tate.org.uk/art/artworks/frink-horseman-robed-t07421"},"classification":"sculpture","credits":"Presented by Lin Jammet, the artist's son 1998"}