{"type":"TATE","from":"Tate Modern museum","artiste":"Ben Nicholson OM","artisteBio":"","date":"1933","title":"Jan 27 1933","subTitle":"","medium":"Oil paint, graphite, paper doily and printed paper on canvas","dimensions":"support: 891 x 683 x 29 mm\r\nframe: 1113 x 908 x 63 mm","medias":{"mini":"http://www.tate.org.uk/art/images/work/T/T07/T07595_8.jpg","medium":"http://www.tate.org.uk/art/images/work/T/T07/T07595_9.jpg","max":"http://www.tate.org.uk/art/images/work/T/T07/T07595_10.jpg","page":"http://www.tate.org.uk/art/artworks/nicholson-jan-27-1933-t07595"},"classification":"painting","credits":"Purchased with assistance from Mrs John Chandris and a group of donors 2000"}