{"type":"TATE","from":"Tate Modern museum","artiste":"Alexander Cozens","artisteBio":"","date":"date not known","title":"Coast Line with Ruined Town, to Left","subTitle":"","medium":"Graphite and watercolour on paper","dimensions":"support: 99 x 159 mm","medias":{"mini":"http://www.tate.org.uk/art/images/work/T/T08/T08021_8.jpg","medium":"http://www.tate.org.uk/art/images/work/T/T08/T08021_9.jpg","max":"http://www.tate.org.uk/art/images/work/T/T08/T08021_10.jpg","page":"http://www.tate.org.uk/art/artworks/cozens-coast-line-with-ruined-town-to-left-t08021"},"classification":"on paper, unique","credits":"Purchased as part of the Oppé Collection with assistance from the National Lottery through the Heritage Lottery Fund 1996"}