{"type":"TATE","from":"Tate Modern museum","artiste":"Thomas Rowlandson","artisteBio":"","date":"1776","title":"A Bench of Artists","subTitle":"","medium":"Ink and graphite on paper","dimensions":"support: 272 x 548 mm","medias":{"mini":"http://www.tate.org.uk/art/images/work/T/T08/T08142_8.jpg","medium":"http://www.tate.org.uk/art/images/work/T/T08/T08142_9.jpg","max":"http://www.tate.org.uk/art/images/work/T/T08/T08142_10.jpg","page":"http://www.tate.org.uk/art/artworks/rowlandson-a-bench-of-artists-t08142"},"classification":"on paper, unique","credits":"Purchased as part of the Oppé Collection with assistance from the National Lottery through the Heritage Lottery Fund 1996"}