{"type":"TATE","from":"Tate Modern museum","artiste":"J.S. Laing","artisteBio":"","date":"date not known","title":"Figure of Christ from the Tympanum at Vezelay","subTitle":"","medium":"Ink on paper","dimensions":"support: 175 x 145 mm","medias":{"mini":"http://www.tate.org.uk/art/images/work/T/T09/T09080_8.jpg","medium":"http://www.tate.org.uk/art/images/work/T/T09/T09080_9.jpg","max":"http://www.tate.org.uk/art/images/work/T/T09/T09080_10.jpg","page":"http://www.tate.org.uk/art/artworks/laing-figure-of-christ-from-the-tympanum-at-vezelay-t09080"},"classification":"on paper, unique","credits":"Purchased as part of the Oppé Collection with assistance from the National Lottery through the Heritage Lottery Fund 1996"}