{"type":"TATE","from":"Tate Modern museum","artiste":"Sir Robert Ker Porter","artisteBio":"","date":"1806","title":"Figure of an Oriental","subTitle":"","medium":"Graphite and watercolour on paper","dimensions":"support: 258 x 181 mm","medias":{"mini":"http://www.tate.org.uk/art/images/work/T/T09/T09150_8.jpg","medium":"http://www.tate.org.uk/art/images/work/T/T09/T09150_9.jpg","max":"http://www.tate.org.uk/art/images/work/T/T09/T09150_10.jpg","page":"http://www.tate.org.uk/art/artworks/porter-figure-of-an-oriental-t09150"},"classification":"on paper, unique","credits":"Purchased as part of the Oppé Collection with assistance from the National Lottery through the Heritage Lottery Fund 1996"}