{"type":"TATE","from":"Tate Modern museum","artiste":"William Marlow","artisteBio":"","date":"date not known","title":"Naples","subTitle":"","medium":"Graphite on paper","dimensions":"support: 125 x 326 mm","medias":{"mini":"http://www.tate.org.uk/art/images/work/T/T09/T09185_8.jpg","medium":"http://www.tate.org.uk/art/images/work/T/T09/T09185_9.jpg","max":"http://www.tate.org.uk/art/images/work/T/T09/T09185_10.jpg","page":"http://www.tate.org.uk/art/artworks/marlow-naples-t09185"},"classification":"on paper, unique","credits":"Purchased as part of the Oppé Collection with assistance from the National Lottery through the Heritage Lottery Fund 1996"}