{"type":"TATE","from":"Tate Modern museum","artiste":"attributed to W. Oram","artisteBio":"","date":"date not known","title":"Ideal Landscape","subTitle":"","medium":"Graphite, ink, watercolour and gouache on paper","dimensions":"support: 153 x 181 mm","medias":{"mini":"http://www.tate.org.uk/art/images/work/T/T09/T09397_8.jpg","medium":"http://www.tate.org.uk/art/images/work/T/T09/T09397_9.jpg","max":"http://www.tate.org.uk/art/images/work/T/T09/T09397_10.jpg","page":"http://www.tate.org.uk/art/artworks/oram-ideal-landscape-t09397"},"classification":"on paper, unique","credits":"Purchased as part of the Oppé Collection with assistance from the National Lottery through the Heritage Lottery Fund 1996"}