{"type":"TATE","from":"Tate Modern museum","artiste":"Rev. William Henry Barnard","artisteBio":"","date":"date not known","title":"A Castellated Mill on a Waterfall","subTitle":"","medium":"Graphite, watercolour and ink on paper","dimensions":"support: 245 x 192 mm","medias":{"mini":"http://www.tate.org.uk/art/images/work/T/T09/T09426_8.jpg","medium":"http://www.tate.org.uk/art/images/work/T/T09/T09426_9.jpg","max":"http://www.tate.org.uk/art/images/work/T/T09/T09426_10.jpg","page":"http://www.tate.org.uk/art/artworks/barnard-a-castellated-mill-on-a-waterfall-t09426"},"classification":"on paper, unique","credits":"Purchased as part of the Oppé Collection with assistance from the National Lottery through the Heritage Lottery Fund 1996"}