{"type":"TATE","from":"Tate Modern museum","artiste":"Giles Hussey","artisteBio":"","date":"date not known","title":"Academy, Standing Figure","subTitle":"","medium":"Graphite, ink and watercolour on paper","dimensions":"support: 244 x 133 mm","medias":{"mini":"http://www.tate.org.uk/art/images/work/T/T09/T09436_8.jpg","medium":"http://www.tate.org.uk/art/images/work/T/T09/T09436_9.jpg","max":"http://www.tate.org.uk/art/images/work/T/T09/T09436_10.jpg","page":"http://www.tate.org.uk/art/artworks/hussey-academy-standing-figure-t09436"},"classification":"on paper, unique","credits":"Purchased as part of the Oppé Collection with assistance from the National Lottery through the Heritage Lottery Fund 1996"}