{"type":"TATE","from":"Tate Modern museum","artiste":"attributed to John Henderson","artisteBio":"","date":"date not known","title":"A French Peasant Woman","subTitle":"","medium":"Graphite and ink on paper","dimensions":"support: 123 x 73 mm","medias":{"mini":"http://www.tate.org.uk/art/images/work/T/T09/T09458_8.jpg","medium":"http://www.tate.org.uk/art/images/work/T/T09/T09458_9.jpg","max":"http://www.tate.org.uk/art/images/work/T/T09/T09458_10.jpg","page":"http://www.tate.org.uk/art/artworks/henderson-a-french-peasant-woman-t09458"},"classification":"on paper, unique","credits":"Purchased as part of the Oppé Collection with assistance from the National Lottery through the Heritage Lottery Fund 1996"}