{"type":"TATE","from":"Tate Modern museum","artiste":"British School 18th century","artisteBio":"","date":"date not known","title":"Caricature of Charles James Fox","subTitle":"","medium":"Ink and watercolour on paper","dimensions":"support: 281 x 234 mm","medias":{"mini":"http://www.tate.org.uk/art/images/work/T/T10/T10104_8.jpg","medium":"http://www.tate.org.uk/art/images/work/T/T10/T10104_9.jpg","max":"http://www.tate.org.uk/art/images/work/T/T10/T10104_10.jpg","page":"http://www.tate.org.uk/art/artworks/british-school-18th-century-caricature-of-charles-james-fox-t10104"},"classification":"on paper, unique","credits":"Purchased as part of the Oppé Collection with assistance from the National Lottery through the Heritage Lottery Fund 1996"}