{"type":"TATE","from":"Tate Modern museum","artiste":"Henry Edridge","artisteBio":"","date":"date not known","title":"Wells. A Gothic Gateway and Old Houses, the Tower of the Cathedral Just Visible","subTitle":"","medium":"Graphite on paper","dimensions":"support: 185 x 249 mm","medias":{"mini":"http://www.tate.org.uk/art/images/work/T/T10/T10102_8.jpg","medium":"http://www.tate.org.uk/art/images/work/T/T10/T10102_9.jpg","max":"http://www.tate.org.uk/art/images/work/T/T10/T10102_10.jpg","page":"http://www.tate.org.uk/art/artworks/edridge-wells-a-gothic-gateway-and-old-houses-the-tower-of-the-cathedral-just-visible-t10102"},"classification":"on paper, unique","credits":"Purchased as part of the Oppé Collection with assistance from the National Lottery through the Heritage Lottery Fund 1996"}