{"type":"TATE","from":"Tate Modern museum","artiste":"Lady Susan Elizabeth Percy","artisteBio":"","date":"1799","title":"Barking Hall Suffolk","subTitle":"","medium":"Graphite and watercolour on paper","dimensions":"support: 150 x 217 mm","medias":{"mini":"http://www.tate.org.uk/art/images/work/T/T10/T10697_8.jpg","medium":"http://www.tate.org.uk/art/images/work/T/T10/T10697_9.jpg","max":"http://www.tate.org.uk/art/images/work/T/T10/T10697_10.jpg","page":"http://www.tate.org.uk/art/artworks/percy-barking-hall-suffolk-t10697"},"classification":"on paper, unique","credits":"Purchased as part of the Oppé Collection with assistance from the National Lottery through the Heritage Lottery Fund 1996"}