{"type":"TATE","from":"Tate Modern museum","artiste":"British (?) School","artisteBio":"","date":"date not known","title":"[title not known]","subTitle":"","medium":"Etching on paper","dimensions":"image: 94 x 96 mm","medias":{"mini":"http://www.tate.org.uk/art/images/work/T/T11/T11336_8.jpg","medium":"http://www.tate.org.uk/art/images/work/T/T11/T11336_9.jpg","max":"http://www.tate.org.uk/art/images/work/T/T11/T11336_10.jpg","page":"http://www.tate.org.uk/art/artworks/british-school-title-not-known-t11336"},"classification":"on paper, print","credits":"Purchased as part of the Oppé Collection with assistance from the National Lottery through the Heritage Lottery Fund 1996"}