{"type":"TATE","from":"Tate Modern museum","artiste":"Alexander Cozens","artisteBio":"","date":"date not known","title":"38. [title not known]","subTitle":"","medium":"Aquatint on paper","dimensions":"image: 225 x 305 mm","medias":{"mini":"http://www.tate.org.uk/art/images/work/T/T11/T11485_8.jpg","medium":"http://www.tate.org.uk/art/images/work/T/T11/T11485_9.jpg","max":"http://www.tate.org.uk/art/images/work/T/T11/T11485_10.jpg","page":"http://www.tate.org.uk/art/artworks/cozens-38-title-not-known-t11485"},"classification":"on paper, print","credits":"Purchased as part of the Oppé Collection with assistance from the National Lottery through the Heritage Lottery Fund 1996"}