{"type":"TATE","from":"Tate Modern museum","artiste":"Rodney Graham","artisteBio":"","date":"1999","title":"How I Became a Ramblin’ Man","subTitle":"","medium":"Film, 35 mm, shown as video, projection, colour and sound","dimensions":"duration: 9 min loop\r\noverall display dimensions variable","medias":{"mini":"http://www.tate.org.uk/art/images/work/T/T12/T12055_8.jpg","medium":"http://www.tate.org.uk/art/images/work/T/T12/T12055_9.jpg","max":"http://www.tate.org.uk/art/images/work/T/T12/T12055_10.jpg","page":"http://www.tate.org.uk/art/artworks/graham-how-i-became-a-ramblin-man-t12055"},"classification":"installation","credits":"Purchased with funds provided by the Mary Joy Thomson Bequest 2005"}