{"type":"TATE","from":"Tate Modern museum","artiste":"David Shrigley","artisteBio":"","date":"2003","title":"Untitled","subTitle":"","medium":"Gouache and ink on paper","dimensions":"support: 297 x 208 mm\r\nframe: 362 x 275 x 38 mm","medias":{"mini":"http://www.tate.org.uk/art/images/work/T/T12/T12361_8.jpg","medium":"http://www.tate.org.uk/art/images/work/T/T12/T12361_9.jpg","max":"http://www.tate.org.uk/art/images/work/T/T12/T12361_10.jpg","page":"http://www.tate.org.uk/art/artworks/shrigley-untitled-t12361"},"classification":"on paper, unique","credits":"Purchased using funds provided by the 2006 Outset / Frieze Art Fair Fund to benefit the Tate Collection 2007"}