{"type":"TATE","from":"Tate Modern museum","artiste":"David Shrigley","artisteBio":"","date":"1999","title":"Untitled","subTitle":"","medium":"Ink on paper","dimensions":"support: 210 x 127 mm\r\nimage: 210 x 127 mm\r\nframe: 268 x 198 x 38 mm","medias":{"mini":"http://www.tate.org.uk/art/images/work/T/T12/T12359_8.jpg","medium":"http://www.tate.org.uk/art/images/work/T/T12/T12359_9.jpg","max":"http://www.tate.org.uk/art/images/work/T/T12/T12359_10.jpg","page":"http://www.tate.org.uk/art/artworks/shrigley-untitled-t12359"},"classification":"on paper, unique","credits":"Purchased using funds provided by the 2006 Outset / Frieze Art Fair Fund to benefit the Tate Collection 2007"}