{"type":"TATE","from":"Tate Modern museum","artiste":"Mahmoud Bakhshi Moakhar","artisteBio":"","date":"2004–6","title":"Air Pollution of Iran","subTitle":"","medium":"8 synthetic fabric flags","dimensions":"object, each: 2350 x 1390 x 55 mm","medias":{"mini":"http://www.tate.org.uk/art/images/work/T/T13/T13191_8.jpg","medium":"http://www.tate.org.uk/art/images/work/T/T13/T13191_9.jpg","max":"http://www.tate.org.uk/art/images/work/T/T13/T13191_10.jpg","page":"http://www.tate.org.uk/art/artworks/bakhshi-moakhar-air-pollution-of-iran-t13191"},"classification":"installation","credits":"Purchased using funds provided by the Middle East North Africa Acquisitions Committee 2010"}