{"type":"TATE","from":"Tate Modern museum","artiste":"Sir William Orpen","artisteBio":"","date":"1900","title":"The Mirror","subTitle":"","medium":"Oil paint on canvas","dimensions":"support: 508 x 406 mm\r\nframe: 682 x 580 x 75 mm","medias":{"mini":"http://www.tate.org.uk/art/images/work/N/N02/N02940_8.jpg","medium":"http://www.tate.org.uk/art/images/work/N/N02/N02940_9.jpg","max":"http://www.tate.org.uk/art/images/work/N/N02/N02940_10.jpg","page":"http://www.tate.org.uk/art/artworks/orpen-the-mirror-n02940"},"classification":"painting","credits":"Presented by Mrs Coutts Michie through the Art Fund in memory of the George McCulloch Collection 1913"}