{"type":"TATE","from":"Tate Modern museum","artiste":"John Sell Cotman","artisteBio":"","date":"1818","title":"North-West View of the Castle at Falaise","subTitle":"","medium":"Graphite and watercolour on paper","dimensions":"support: 194 x 387 mm","medias":{"mini":"http://www.tate.org.uk/art/images/work/N/N03/N03329_8.jpg","medium":"http://www.tate.org.uk/art/images/work/N/N03/N03329_9.jpg","max":"http://www.tate.org.uk/art/images/work/N/N03/N03329_10.jpg","page":"http://www.tate.org.uk/art/artworks/cotman-north-west-view-of-the-castle-at-falaise-n03329"},"classification":"on paper, unique","credits":"Presented by Sir Jeremiah Colman Bt through the Art Fund 1918"}