{"type":"TATE","from":"Tate Modern museum","artiste":"A. Neville Lewis","artisteBio":"","date":"exhibited 1923","title":"Charlie, a Little Gipsy Boy","subTitle":"","medium":"Oil paint on canvas","dimensions":"support: 356 x 254 mm","medias":{"mini":"http://www.tate.org.uk/art/images/work/N/N03/N03841_8.jpg","medium":"http://www.tate.org.uk/art/images/work/N/N03/N03841_9.jpg","max":"http://www.tate.org.uk/art/images/work/N/N03/N03841_10.jpg","page":"http://www.tate.org.uk/art/artworks/lewis-charlie-a-little-gipsy-boy-n03841"},"classification":"painting","credits":"Presented by the Contemporary Art Society 1924"}