{"type":"TATE","from":"Tate Modern museum","artiste":"Charles Samuel Keene","artisteBio":"","date":"date not known","title":"Butcher’s Shop","subTitle":"","medium":"Ink on paper","dimensions":"support: 111 x 171 mm","medias":{"mini":"http://www.tate.org.uk/art/images/work/N/N04/N04073_8.jpg","medium":"http://www.tate.org.uk/art/images/work/N/N04/N04073_9.jpg","max":"http://www.tate.org.uk/art/images/work/N/N04/N04073_10.jpg","page":"http://www.tate.org.uk/art/artworks/keene-butchers-shop-n04073"},"classification":"on paper, unique","credits":"Presented by the Misses Arber 1925"}