{"type":"TATE","from":"Tate Modern museum","artiste":"Arthur Boyd Houghton","artisteBio":"","date":"c.1865","title":"Facing the Camera, for engraving","subTitle":"","medium":"Ink and gouache on woodblock","dimensions":"support: 133 x 102 mm","medias":{"mini":"http://www.tate.org.uk/art/images/work/N/N04/N04159_8.jpg","medium":"http://www.tate.org.uk/art/images/work/N/N04/N04159_9.jpg","max":"http://www.tate.org.uk/art/images/work/N/N04/N04159_10.jpg","page":"http://www.tate.org.uk/art/artworks/houghton-facing-the-camera-for-engraving-n04159"},"classification":"painting","credits":"Presented by Mrs E.C. Davis 1926"}