{"type":"TATE","from":"Tate Modern museum","artiste":"Paul Troubetzkoy","artisteBio":"","date":"1926","title":"George Bernard Shaw","subTitle":"","medium":"Bronze","dimensions":"object: 594 x 365 x 267 mm","medias":{"mini":"http://www.tate.org.uk/art/images/work/N/N04/N04274_8.jpg","medium":"http://www.tate.org.uk/art/images/work/N/N04/N04274_9.jpg","max":"http://www.tate.org.uk/art/images/work/N/N04/N04274_10.jpg","page":"http://www.tate.org.uk/art/artworks/troubetzkoy-george-bernard-shaw-n04274"},"classification":"sculpture","credits":"Presented by Mrs George Bernard Shaw 1927"}