{"type":"TATE","from":"Tate Modern museum","artiste":"Joseph Mallord William Turner","artisteBio":"","date":"c.1840","title":"Seascape with Storm Coming On","subTitle":"","medium":"Oil paint on canvas","dimensions":"support: 914 x 1216 mm\r\nframe: 1122 x 1448 x 82 mm","medias":{"mini":"http://www.tate.org.uk/art/images/work/N/N04/N04445_8.jpg","medium":"http://www.tate.org.uk/art/images/work/N/N04/N04445_9.jpg","max":"http://www.tate.org.uk/art/images/work/N/N04/N04445_10.jpg","page":"http://www.tate.org.uk/art/artworks/turner-seascape-with-storm-coming-on-n04445"},"classification":"painting","credits":"Accepted by the nation as part of the Turner Bequest 1856"}