{"type":"TATE","from":"Tate Modern museum","artiste":"Christopher Richard Wynne Nevinson","artisteBio":"","date":"1923–4","title":"Fitzroy Square","subTitle":"","medium":"Oil paint on wood","dimensions":"support: 381 x 276 mm","medias":{"mini":"http://www.tate.org.uk/art/images/work/N/N04/N04979_8.jpg","medium":"http://www.tate.org.uk/art/images/work/N/N04/N04979_9.jpg","max":"http://www.tate.org.uk/art/images/work/N/N04/N04979_10.jpg","page":"http://www.tate.org.uk/art/artworks/nevinson-fitzroy-square-n04979"},"classification":"painting","credits":"Presented by D.C. Fincham 1939"}