{"type":"TATE","from":"Tate Modern museum","artiste":"Derwent Lees","artisteBio":"","date":"1912","title":"Métairie des Abeilles","subTitle":"","medium":"Oil paint on wood","dimensions":"support: 330 x 406 mm","medias":{"mini":"http://www.tate.org.uk/art/images/work/N/N05/N05355_8.jpg","medium":"http://www.tate.org.uk/art/images/work/N/N05/N05355_9.jpg","max":"http://www.tate.org.uk/art/images/work/N/N05/N05355_10.jpg","page":"http://www.tate.org.uk/art/artworks/lees-metairie-des-abeilles-n05355"},"classification":"painting","credits":"Bequeathed by Dr John MacGregor 1942"}