{"type":"TATE","from":"Tate Modern museum","artiste":"Mark Gertler","artisteBio":"","date":"1911","title":"The Artist’s Mother","subTitle":"","medium":"Oil paint on canvas","dimensions":"support: 660 x 559 mm\r\nframe: 873 x 785 x 87 mm","medias":{"mini":"http://www.tate.org.uk/art/images/work/N/N05/N05557_8.jpg","medium":"http://www.tate.org.uk/art/images/work/N/N05/N05557_9.jpg","max":"http://www.tate.org.uk/art/images/work/N/N05/N05557_10.jpg","page":"http://www.tate.org.uk/art/artworks/gertler-the-artists-mother-n05557"},"classification":"painting","credits":"Presented by the Trustees of the Chantrey Bequest 1944"}