{"type":"TATE","from":"Tate Modern museum","artiste":"Rex Whistler","artisteBio":"","date":"c.1933","title":"Self-Portrait","subTitle":"","medium":"Oil paint on canvas","dimensions":"support: 406 x 368 mm\r\nframe: 473 x 437 x 53 mm","medias":{"mini":"http://www.tate.org.uk/art/images/work/N/N05/N05865_8.jpg","medium":"http://www.tate.org.uk/art/images/work/N/N05/N05865_9.jpg","max":"http://www.tate.org.uk/art/images/work/N/N05/N05865_10.jpg","page":"http://www.tate.org.uk/art/artworks/whistler-self-portrait-n05865"},"classification":"painting","credits":"Bequeathed by Miss Edith Olivier 1948"}