{"type":"TATE","from":"Tate Modern museum","artiste":"Carel Weight","artisteBio":"","date":"1953","title":"The Rendezvous","subTitle":"","medium":"Oil paint on canvas","dimensions":"support: 860 x 1110 mm","medias":{"mini":"http://www.tate.org.uk/art/images/work/N/N06/N06177_8.jpg","medium":"http://www.tate.org.uk/art/images/work/N/N06/N06177_9.jpg","max":"http://www.tate.org.uk/art/images/work/N/N06/N06177_10.jpg","page":"http://www.tate.org.uk/art/artworks/weight-the-rendezvous-n06177"},"classification":"painting","credits":"Presented by the Trustees of the Chantrey Bequest 1953"}