{"type":"TATE","from":"Tate Modern museum","artiste":"Martin Bloch","artisteBio":"","date":"1948–50","title":"The Mississippi at Minneapolis","subTitle":"","medium":"Oil paint on canvas","dimensions":"support: 711 x 921 mm\r\nframe: 917 x 1118 x 100 mm","medias":{"mini":"http://www.tate.org.uk/art/images/work/N/N06/N06235_8.jpg","medium":"http://www.tate.org.uk/art/images/work/N/N06/N06235_9.jpg","max":"http://www.tate.org.uk/art/images/work/N/N06/N06235_10.jpg","page":"http://www.tate.org.uk/art/artworks/bloch-the-mississippi-at-minneapolis-n06235"},"classification":"painting","credits":"Purchased 1954"}