{"type":"TATE","from":"Tate Modern museum","artiste":"Barnett Newman","artisteBio":"","date":"1963–4","title":"Canto X","subTitle":"","medium":"Lithograph on paper","dimensions":"image: 373 x 337 mm","medias":{"mini":"http://www.tate.org.uk/art/images/work/P/P01/P01036_8.jpg","medium":"http://www.tate.org.uk/art/images/work/P/P01/P01036_9.jpg","max":"http://www.tate.org.uk/art/images/work/P/P01/P01036_10.jpg","page":"http://www.tate.org.uk/art/artworks/newman-canto-x-p01036"},"classification":"on paper, print","credits":"Presented by Mrs Annalee Newman, the artist's widow 1972"}