{"type":"TATE","from":"Tate Modern museum","artiste":"Robert Blake","artisteBio":"","date":"?c.1785","title":"The Preaching of Warning. Verso: An Old Man Enthroned Between Two Groups of Figures, by ?William Blake","subTitle":"","medium":"Graphite on paper. Verso: graphite on paper","dimensions":"support: 343 x 467 mm","medias":{"mini":"http://www.tate.org.uk/art/images/work/A/A00/A00003_8.jpg","medium":"http://www.tate.org.uk/art/images/work/A/A00/A00003_9.jpg","max":"http://www.tate.org.uk/art/images/work/A/A00/A00003_10.jpg","page":"http://www.tate.org.uk/art/artworks/blake-the-preaching-of-warning-verso-an-old-man-enthroned-between-two-groups-of-figures-by-a00003"},"classification":"on paper, unique","credits":"Presented by Mrs John Richmond 1922"}