{"type":"TATE","from":"Tate Modern museum","artiste":"Frederick Sandys","artisteBio":"","date":"date not known","title":"Melancholia","subTitle":"","medium":"Relief print on paper","dimensions":"support: 105 x 140 mm","medias":{"mini":"http://www.tate.org.uk/art/images/work/A/A00/A00847_8.jpg","medium":"http://www.tate.org.uk/art/images/work/A/A00/A00847_9.jpg","max":"http://www.tate.org.uk/art/images/work/A/A00/A00847_10.jpg","page":"http://www.tate.org.uk/art/artworks/sandys-melancholia-a00847"},"classification":"on paper, unique","credits":"Presented by J.R. Holliday 1927"}