{"type":"TATE","from":"Tate Modern museum","artiste":"Joseph Mallord William Turner","artisteBio":"","date":"1808","title":"Dunstanborough Castle","subTitle":"","medium":"Etching and engraving on paper","dimensions":"image: 182 x 263 mm","medias":{"mini":"http://www.tate.org.uk/art/images/work/A/A00/A00937_8.jpg","medium":"http://www.tate.org.uk/art/images/work/A/A00/A00937_9.jpg","max":"http://www.tate.org.uk/art/images/work/A/A00/A00937_10.jpg","page":"http://www.tate.org.uk/art/artworks/turner-dunstanborough-castle-a00937"},"classification":"on paper, print","credits":"Presented by A. Acland Allen through the Art Fund 1925"}