{"type":"TATE","from":"Tate Modern museum","artiste":"Edward Ardizzone","artisteBio":"","date":"1931","title":"At the Brasserie","subTitle":"","medium":"Watercolour and ink on paper","dimensions":"support: 152 x 222 mm","medias":{"mini":"http://www.tate.org.uk/art/images/work/A/A01/A01029_8.jpg","medium":"http://www.tate.org.uk/art/images/work/A/A01/A01029_9.jpg","max":"http://www.tate.org.uk/art/images/work/A/A01/A01029_10.jpg","page":"http://www.tate.org.uk/art/artworks/ardizzone-at-the-brasserie-a01029"},"classification":"on paper, unique","credits":"Purchased 1940"}