{"type":"TATE","from":"Tate Modern museum","artiste":"Ian Hamilton Finlay","artisteBio":"","date":"1986","title":"IDYLLS END IN THUNDERSTORMS","subTitle":"","medium":"Wall text","dimensions":"Overall displayed dimensions variable","medias":{"mini":"http://www.tate.org.uk/art/images/work/AR/AR01124_8.jpg","medium":"http://www.tate.org.uk/art/images/work/AR/AR01124_9.jpg","max":"http://www.tate.org.uk/art/images/work/AR/AR01124_10.jpg","page":"http://www.tate.org.uk/art/artworks/hamilton-finlay-idylls-end-in-thunderstorms-ar01124"},"classification":"installation","credits":"ARTIST ROOMS\r\nTate and National Galleries of Scotland. Presented by the artist's estate 2010"}