{"type":"TATE","from":"Tate Modern museum","artiste":"Joseph Mallord William Turner","artisteBio":"","date":"1794","title":"Shrewsbury: The Town seen from the River with the New English Bridge in the Foreground","subTitle":"","medium":"Graphite on paper","dimensions":"support: 216 x 274 mm","medias":{"mini":"http://www.tate.org.uk/art/images/work/D/D00/D00331_8.jpg","medium":"http://www.tate.org.uk/art/images/work/D/D00/D00331_9.jpg","max":"http://www.tate.org.uk/art/images/work/D/D00/D00331_10.jpg","page":"http://www.tate.org.uk/art/artworks/turner-shrewsbury-the-town-seen-from-the-river-with-the-new-english-bridge-in-the-d00331"},"classification":"on paper, unique","credits":"Accepted by the nation as part of the Turner Bequest 1856"}