{"type":"TATE","from":"Tate Modern museum","artiste":"Barry Flanagan","artisteBio":"","date":"1970, reprinted c.1983","title":"To Draw Fire","subTitle":"","medium":"Etching and aquatint on paper","dimensions":"image: 247 x 245 mm","medias":{"mini":"http://www.tate.org.uk/art/images/work/P/P02/P02728_8.jpg","medium":"http://www.tate.org.uk/art/images/work/P/P02/P02728_9.jpg","max":"http://www.tate.org.uk/art/images/work/P/P02/P02728_10.jpg","page":"http://www.tate.org.uk/art/artworks/flanagan-to-draw-fire-p02728"},"classification":"on paper, print","credits":"Presented by Sue Flanagan, the artist's former wife 1985"}