{"type":"TATE","from":"Tate Modern museum","artiste":"Joseph Mallord William Turner","artisteBio":"","date":"?1798","title":"A Cart and Horses in a Quarry","subTitle":"","medium":"Graphite on paper","dimensions":"support: 204 x 264 mm","medias":{"mini":"http://www.tate.org.uk/art/images/work/D/D00/D00461_8.jpg","medium":"http://www.tate.org.uk/art/images/work/D/D00/D00461_9.jpg","max":"http://www.tate.org.uk/art/images/work/D/D00/D00461_10.jpg","page":"http://www.tate.org.uk/art/artworks/turner-a-cart-and-horses-in-a-quarry-d00461"},"classification":"on paper, unique","credits":"Accepted by the nation as part of the Turner Bequest 1856"}