{"type":"TATE","from":"Tate Modern museum","artiste":"Joseph Mallord William Turner","artisteBio":"","date":"1797","title":"Patterdale Old Church, Looking North to the Lake","subTitle":"","medium":"Graphite on paper","dimensions":"support: 368 x 262 mm","medias":{"mini":"http://www.tate.org.uk/art/images/work/D/D01/D01046_8.jpg","medium":"http://www.tate.org.uk/art/images/work/D/D01/D01046_9.jpg","max":"http://www.tate.org.uk/art/images/work/D/D01/D01046_10.jpg","page":"http://www.tate.org.uk/art/artworks/turner-patterdale-old-church-looking-north-to-the-lake-d01046"},"classification":"on paper, unique","credits":"Accepted by the nation as part of the Turner Bequest 1856"}