{"type":"TATE","from":"Tate Modern museum","artiste":"Joseph Mallord William Turner","artisteBio":"","date":"1796–7","title":"A Fishing Boat Running before the Wind","subTitle":"","medium":"Gouache, graphite and watercolour on paper","dimensions":"support: 113 x 93 mm","medias":{"mini":"http://www.tate.org.uk/art/images/work/D/D01/D01225_8.jpg","medium":"http://www.tate.org.uk/art/images/work/D/D01/D01225_9.jpg","max":"http://www.tate.org.uk/art/images/work/D/D01/D01225_10.jpg","page":"http://www.tate.org.uk/art/artworks/turner-a-fishing-boat-running-before-the-wind-d01225"},"classification":"on paper, unique","credits":"Accepted by the nation as part of the Turner Bequest 1856"}