{"type":"TATE","from":"Tate Modern museum","artiste":"Joseph Mallord William Turner","artisteBio":"","date":"1802","title":"Martigny: La Bâtiaz Overlooking a Street in the Town","subTitle":"","medium":"Chalk, gouache and graphite on paper","dimensions":"support: 285 x 212 mm","medias":{"mini":"http://www.tate.org.uk/art/images/work/D/D04/D04547_8.jpg","medium":"http://www.tate.org.uk/art/images/work/D/D04/D04547_9.jpg","max":"http://www.tate.org.uk/art/images/work/D/D04/D04547_10.jpg","page":"http://www.tate.org.uk/art/artworks/turner-martigny-la-batiaz-overlooking-a-street-in-the-town-d04547"},"classification":"on paper, unique","credits":"Accepted by the nation as part of the Turner Bequest 1856"}