{"type":"TATE","from":"Tate Modern museum","artiste":"Joseph Mallord William Turner","artisteBio":"","date":"1805","title":"Diagram of the Quarterdeck of the ‘Victory’ with Positions of Nelson and Others at the Battle of Trafalgar","subTitle":"","medium":"Graphite on paper","dimensions":"support: 184 x 114 mm","medias":{"mini":"http://www.tate.org.uk/art/images/work/D/D05/D05469_8.jpg","medium":"http://www.tate.org.uk/art/images/work/D/D05/D05469_9.jpg","max":"http://www.tate.org.uk/art/images/work/D/D05/D05469_10.jpg","page":"http://www.tate.org.uk/art/artworks/turner-diagram-of-the-quarterdeck-of-the-victory-with-positions-of-nelson-and-others-at-d05469"},"classification":"on paper, unique","credits":"Accepted by the nation as part of the Turner Bequest 1856"}