{"type":"TATE","from":"Tate Modern museum","artiste":"Geoffrey Clarke","artisteBio":"","date":"1950","title":"The Family","subTitle":"","medium":"Intaglio print on paper","dimensions":"image: 352 x 200 mm","medias":{"mini":"http://www.tate.org.uk/art/images/work/P/P03/P03162_8.jpg","medium":"http://www.tate.org.uk/art/images/work/P/P03/P03162_9.jpg","max":"http://www.tate.org.uk/art/images/work/P/P03/P03162_10.jpg","page":"http://www.tate.org.uk/art/artworks/clarke-the-family-p03162"},"classification":"on paper, print","credits":"Presented by Taranman Gallery 1976"}