{"type":"TATE","from":"Tate Modern museum","artiste":"Joseph Mallord William Turner","artisteBio":"","date":"1805","title":"The River Thames and Kew Bridge, with Brentford Eyot in the Foreground and Strand-on-Green Seen through the Arches: Low Tide","subTitle":"","medium":"Graphite and watercolour on paper","dimensions":"support: 256 x 364 mm","medias":{"mini":"http://www.tate.org.uk/art/images/work/D/D05/D05946_8.jpg","medium":"http://www.tate.org.uk/art/images/work/D/D05/D05946_9.jpg","max":"http://www.tate.org.uk/art/images/work/D/D05/D05946_10.jpg","page":"http://www.tate.org.uk/art/artworks/turner-the-river-thames-and-kew-bridge-with-brentford-eyot-in-the-foreground-and-strand-on-d05946"},"classification":"on paper, unique","credits":"Accepted by the nation as part of the Turner Bequest 1856"}